mkdocs_link_cards/__init__.py
mkdocs_link_cards/plugin.py
mkdocs_link_cards-0.1.0.dist-info/METADATA
mkdocs_link_cards-0.1.0.dist-info/WHEEL
mkdocs_link_cards-0.1.0.dist-info/entry_points.txt
mkdocs_link_cards-0.1.0.dist-info/licenses/LICENSE
mkdocs_link_cards-0.1.0.dist-info/RECORD
