Metadata-Version: 2.4
Name: mkdocs-link-cards
Version: 0.1.0
Summary: Discord-style link previews (Material cards) for MkDocs at build time.
License: MIT
License-File: LICENSE
Keywords: mkdocs,material,cards,opengraph,oembed,arxiv,youtube
Author: markeyser
Author-email: marcosak@gmail.com
Requires-Python: >=3.10
Classifier: Development Status :: 3 - Alpha
Classifier: Framework :: MkDocs
Classifier: Intended Audience :: Developers
Classifier: License :: OSI Approved :: MIT License
Classifier: Programming Language :: Python
Classifier: Programming Language :: Python :: 3
Classifier: Programming Language :: Python :: 3.10
Classifier: Programming Language :: Python :: 3.11
Classifier: Programming Language :: Python :: 3.12
Classifier: Topic :: Internet :: WWW/HTTP :: Site Management
Provides-Extra: oembed
Provides-Extra: summarize
Requires-Dist: beautifulsoup4 (>=4.12)
Requires-Dist: extruct (>=0.16)
Requires-Dist: micawber (>=0.5.5) ; extra == "oembed"
Requires-Dist: mkdocs (>=1.5)
Requires-Dist: requests (>=2.31)
Requires-Dist: sumy (>=0.11.0) ; extra == "summarize"
Requires-Dist: trafilatura (>=1.8.0) ; extra == "summarize"
Requires-Dist: w3lib (>=2.1)
Project-URL: Homepage, https://github.com/markeyser/mkdocs-link-cards
Project-URL: Issues, https://github.com/markeyser/mkdocs-link-cards/issues
Project-URL: Repository, https://github.com/markeyser/mkdocs-link-cards
